veracross_client/__init__.py
veracross_client/veracross_client.py
veracross_client-0.0.4.dist-info/LICENSE
veracross_client-0.0.4.dist-info/METADATA
veracross_client-0.0.4.dist-info/WHEEL
veracross_client-0.0.4.dist-info/top_level.txt
veracross_client-0.0.4.dist-info/RECORD
