Metadata-Version: 2.1
Name: veracross-client
Version: 0.0.4
Summary: Python wrapper for communicating with the Veracross API
Author: Hudson Harper
Author-email: Hudson Harper <hudson@harpertech.io>
Project-URL: Homepage, https://github.com/hudson-harpertech/veracross-client
Project-URL: Bug Tracker, https://github.com/hudson-harpertech/veracross-client/issues
Classifier: Programming Language :: Python :: 3
Classifier: License :: OSI Approved :: MIT License
Classifier: Operating System :: OS Independent
Requires-Python: >=3.8
License-File: LICENSE
